vmaf_torch/__init__.py
vmaf_torch/adm.py
vmaf_torch/motion.py
vmaf_torch/svm_predict.py
vmaf_torch/utils.py
vmaf_torch/vif.py
vmaf_torch/vmaf.py
vmaf_torch-1.1.0.dist-info/licenses/LICENSE
vmaf_torch-1.1.0.dist-info/METADATA
vmaf_torch-1.1.0.dist-info/WHEEL
vmaf_torch-1.1.0.dist-info/top_level.txt
vmaf_torch-1.1.0.dist-info/RECORD
