Metadata-Version: 2.4
Name: vmaf-torch
Version: 1.1.0
Summary: VMAF implementation in PyTorch
Author-email: Kirill Aistov <kirill.aistov1@huawei.com>
Project-URL: Homepage, https://github.com/alvitrioliks/VMAF-torch
Keywords: VMAF,PyTorch,video quality assessment
Requires-Python: >=3.9
License-File: LICENSE
Requires-Dist: numpy
Requires-Dist: pandas
Requires-Dist: torch
Requires-Dist: yuvio
Dynamic: license-file
